{
  "date": "2026-06-19",
  "pre_screened_count": 1831,
  "picks": [
    {
      "code": "300319",
      "name": "麦捷科技",
      "price": 27.76,
      "score": 7.5,
      "strategies": [
        "💪主力资金#1"
      ],
      "industry": "电子-元件-被动元件"
    },
    {
      "code": "301072",
      "name": "中捷精工",
      "price": 40.61,
      "score": 6.5,
      "strategies": [
        "💪主力资金#2"
      ],
      "industry": "汽车-汽车零部件-底盘与"
    },
    {
      "code": "001696",
      "name": "宗申动力",
      "price": 24.31,
      "score": 5.5,
      "strategies": [
        "💪主力资金#3"
      ],
      "industry": "机械设备-通用设备-其他"
    },
    {
      "code": "300420",
      "name": "五洋自控",
      "price": 7.49,
      "score": 5.0,
      "strategies": [
        "💪主力资金#4"
      ],
      "industry": "机械设备-通用设备-其他"
    },
    {
      "code": "000608",
      "name": "阳光股份",
      "price": 7.59,
      "score": 5.0,
      "strategies": [
        "💪主力资金#5"
      ],
      "industry": "房地产-房地产-商业地产"
    }
  ]
}